[
  {
    "url": "https://api.github.com/repos/g0v/g0village-8bit/issues/31",
    "labels_url": "https://api.github.com/repos/g0v/g0village-8bit/issues/31/labels{/name}",
    "comments_url": "https://api.github.com/repos/g0v/g0village-8bit/issues/31/comments",
    "events_url": "https://api.github.com/repos/g0v/g0village-8bit/issues/31/events",
    "html_url": "https://github.com/g0v/g0village-8bit/issues/31",
    "id": 18543789,
    "number": 31,
    "title": "如何跟售票亭老板領取fire.app?",
    "user": {
      "login": "bestian",
      "id": 109048,
      "avatar_url": "https://gravatar.com/avatar/1ea4fcb48144a97a1f68af6d8a302c47?d=https%3A%2F%2Fidenticons.github.com%2F1de5d1df48f548f9d227c6743af88c42.png&r=x",
      "gravatar_id": "1ea4fcb48144a97a1f68af6d8a302c47",
      "url": "https://api.github.com/users/bestian",
      "html_url": "https://github.com/bestian",
      "followers_url": "https://api.github.com/users/bestian/followers",
      "following_url": "https://api.github.com/users/bestian/following{/other_user}",
      "gists_url": "https://api.github.com/users/bestian/gists{/gist_id}",
      "starred_url": "https://api.github.com/users/bestian/starred{/owner}{/repo}",
      "subscriptions_url": "https://api.github.com/users/bestian/subscriptions",
      "organizations_url": "https://api.github.com/users/bestian/orgs",
      "repos_url": "https://api.github.com/users/bestian/repos",
      "events_url": "https://api.github.com/users/bestian/events{/privacy}",
      "received_events_url": "https://api.github.com/users/bestian/received_events",
      "type": "User",
      "site_admin": false
    },
    "labels": [

    ],
    "state": "open",
    "assignee": null,
    "milestone": null,
    "comments": 4,
    "created_at": "2013-08-26T11:08:56Z",
    "updated_at": "2013-08-27T05:49:19Z",
    "closed_at": null,
    "body": "售票亭老板說可以跟他領，可是沒有附上領取方法?"
  },
  {
    "url": "https://api.github.com/repos/g0v/g0village-8bit/issues/27",
    "labels_url": "https://api.github.com/repos/g0v/g0village-8bit/issues/27/labels{/name}",
    "comments_url": "https://api.github.com/repos/g0v/g0village-8bit/issues/27/comments",
    "events_url": "https://api.github.com/repos/g0v/g0village-8bit/issues/27/events",
    "html_url": "https://github.com/g0v/g0village-8bit/issues/27",
    "id": 18440250,
    "number": 27,
    "title": "建議把bug回報區的連結放在新手村某處",
    "user": {
      "login": "granulation",
      "id": 5289938,
      "avatar_url": "https://gravatar.com/avatar/28f9f4fe1731bbb7c1c4f710f780e473?d=https%3A%2F%2Fidenticons.github.com%2Fc73b5a2cd6e2049455e9f7729c27d1fd.png&r=x",
      "gravatar_id": "28f9f4fe1731bbb7c1c4f710f780e473",
      "url": "https://api.github.com/users/granulation",
      "html_url": "https://github.com/granulation",
      "followers_url": "https://api.github.com/users/granulation/followers",
      "following_url": "https://api.github.com/users/granulation/following{/other_user}",
      "gists_url": "https://api.github.com/users/granulation/gists{/gist_id}",
      "starred_url": "https://api.github.com/users/granulation/starred{/owner}{/repo}",
      "subscriptions_url": "https://api.github.com/users/granulation/subscriptions",
      "organizations_url": "https://api.github.com/users/granulation/orgs",
      "repos_url": "https://api.github.com/users/granulation/repos",
      "events_url": "https://api.github.com/users/granulation/events{/privacy}",
      "received_events_url": "https://api.github.com/users/granulation/received_events",
      "type": "User",
      "site_admin": false
    },
    "labels": [

    ],
    "state": "open",
    "assignee": null,
    "milestone": null,
    "comments": 0,
    "created_at": "2013-08-22T21:09:30Z",
    "updated_at": "2013-08-22T21:09:30Z",
    "closed_at": null,
    "body": "建議把bug回報區的連結放在新手村某處\r\n\r\n不然我都找不到要在哪回報XD"
  },
  {
    "url": "https://api.github.com/repos/g0v/g0village-8bit/issues/26",
    "labels_url": "https://api.github.com/repos/g0v/g0village-8bit/issues/26/labels{/name}",
    "comments_url": "https://api.github.com/repos/g0v/g0village-8bit/issues/26/comments",
    "events_url": "https://api.github.com/repos/g0v/g0village-8bit/issues/26/events",
    "html_url": "https://github.com/g0v/g0village-8bit/issues/26",
    "id": 18439681,
    "number": 26,
    "title": "打村長的時候如果村長喝完所有的咖啡會當機...",
    "user": {
      "login": "granulation",
      "id": 5289938,
      "avatar_url": "https://gravatar.com/avatar/28f9f4fe1731bbb7c1c4f710f780e473?d=https%3A%2F%2Fidenticons.github.com%2Fc73b5a2cd6e2049455e9f7729c27d1fd.png&r=x",
      "gravatar_id": "28f9f4fe1731bbb7c1c4f710f780e473",
      "url": "https://api.github.com/users/granulation",
      "html_url": "https://github.com/granulation",
      "followers_url": "https://api.github.com/users/granulation/followers",
      "following_url": "https://api.github.com/users/granulation/following{/other_user}",
      "gists_url": "https://api.github.com/users/granulation/gists{/gist_id}",
      "starred_url": "https://api.github.com/users/granulation/starred{/owner}{/repo}",
      "subscriptions_url": "https://api.github.com/users/granulation/subscriptions",
      "organizations_url": "https://api.github.com/users/granulation/orgs",
      "repos_url": "https://api.github.com/users/granulation/repos",
      "events_url": "https://api.github.com/users/granulation/events{/privacy}",
      "received_events_url": "https://api.github.com/users/granulation/received_events",
      "type": "User",
      "site_admin": false
    },
    "labels": [

    ],
    "state": "open",
    "assignee": null,
    "milestone": null,
    "comments": 1,
    "created_at": "2013-08-22T20:59:51Z",
    "updated_at": "2013-08-22T21:01:52Z",
    "closed_at": null,
    "body": "打村長的時候如果村長喝完所有的咖啡會當機..."
  },
  {
    "url": "https://api.github.com/repos/g0v/g0village-8bit/issues/23",
    "labels_url": "https://api.github.com/repos/g0v/g0village-8bit/issues/23/labels{/name}",
    "comments_url": "https://api.github.com/repos/g0v/g0village-8bit/issues/23/comments",
    "events_url": "https://api.github.com/repos/g0v/g0village-8bit/issues/23/events",
    "html_url": "https://github.com/g0v/g0village-8bit/issues/23",
    "id": 18333880,
    "number": 23,
    "title": "Add g0v.json",
    "user": {
      "login": "kcwu",
      "id": 175566,
      "avatar_url": "https://gravatar.com/avatar/dcf72ddc903576375b3ffb65290a9d40?d=https%3A%2F%2Fidenticons.github.com%2F98dca029b4b8c0a769519e95d7b632f1.png&r=x",
      "gravatar_id": "dcf72ddc903576375b3ffb65290a9d40",
      "url": "https://api.github.com/users/kcwu",
      "html_url": "https://github.com/kcwu",
      "followers_url": "https://api.github.com/users/kcwu/followers",
      "following_url": "https://api.github.com/users/kcwu/following{/other_user}",
      "gists_url": "https://api.github.com/users/kcwu/gists{/gist_id}",
      "starred_url": "https://api.github.com/users/kcwu/starred{/owner}{/repo}",
      "subscriptions_url": "https://api.github.com/users/kcwu/subscriptions",
      "organizations_url": "https://api.github.com/users/kcwu/orgs",
      "repos_url": "https://api.github.com/users/kcwu/repos",
      "events_url": "https://api.github.com/users/kcwu/events{/privacy}",
      "received_events_url": "https://api.github.com/users/kcwu/received_events",
      "type": "User",
      "site_admin": false
    },
    "labels": [

    ],
    "state": "open",
    "assignee": null,
    "milestone": null,
    "comments": 0,
    "created_at": "2013-08-21T03:05:37Z",
    "updated_at": "2013-08-21T03:05:37Z",
    "closed_at": null,
    "body": "If this project does not belong to http://g0v.tw/ or is not applicable, \r\nyou can ignore and close this bug.\r\n\r\nOtherwise please add g0v.json to your project.\r\nSee https://g0v.hackpad.com/g0v.json-spec-c07sSfauWSc for detail.\r\n\r\nYou can see the progress of adding g0v.json here: g0v/hack.g0v.tw#35"
  },
  {
    "url": "https://api.github.com/repos/g0v/g0village-8bit/issues/21",
    "labels_url": "https://api.github.com/repos/g0v/g0village-8bit/issues/21/labels{/name}",
    "comments_url": "https://api.github.com/repos/g0v/g0village-8bit/issues/21/comments",
    "events_url": "https://api.github.com/repos/g0v/g0village-8bit/issues/21/events",
    "html_url": "https://github.com/g0v/g0village-8bit/issues/21",
    "id": 18192807,
    "number": 21,
    "title": "對話出現空白活動",
    "user": {
      "login": "bcbcarl",
      "id": 135734,
      "avatar_url": "https://gravatar.com/avatar/89aab2f2d2f5fdb2ead734d54bbc7500?d=https%3A%2F%2Fidenticons.github.com%2F6610a9df8b76b17d557adfa9f417082e.png&r=x",
      "gravatar_id": "89aab2f2d2f5fdb2ead734d54bbc7500",
      "url": "https://api.github.com/users/bcbcarl",
      "html_url": "https://github.com/bcbcarl",
      "followers_url": "https://api.github.com/users/bcbcarl/followers",
      "following_url": "https://api.github.com/users/bcbcarl/following{/other_user}",
      "gists_url": "https://api.github.com/users/bcbcarl/gists{/gist_id}",
      "starred_url": "https://api.github.com/users/bcbcarl/starred{/owner}{/repo}",
      "subscriptions_url": "https://api.github.com/users/bcbcarl/subscriptions",
      "organizations_url": "https://api.github.com/users/bcbcarl/orgs",
      "repos_url": "https://api.github.com/users/bcbcarl/repos",
      "events_url": "https://api.github.com/users/bcbcarl/events{/privacy}",
      "received_events_url": "https://api.github.com/users/bcbcarl/received_events",
      "type": "User",
      "site_admin": false
    },
    "labels": [

    ],
    "state": "open",
    "assignee": null,
    "milestone": null,
    "comments": 0,
    "created_at": "2013-08-17T11:26:34Z",
    "updated_at": "2013-08-17T11:36:53Z",
    "closed_at": null,
    "body": "和阿土伯對話幾次，時常有機會出現空白活動，而且還不只一個，這會是 bug 嗎？\r\n![(screenshot)](http://i.imgur.com/7DhL1pI.png)"
  },
  {
    "url": "https://api.github.com/repos/g0v/g0village-8bit/issues/19",
    "labels_url": "https://api.github.com/repos/g0v/g0village-8bit/issues/19/labels{/name}",
    "comments_url": "https://api.github.com/repos/g0v/g0village-8bit/issues/19/comments",
    "events_url": "https://api.github.com/repos/g0v/g0village-8bit/issues/19/events",
    "html_url": "https://github.com/g0v/g0village-8bit/issues/19",
    "id": 18192245,
    "number": 19,
    "title": "萌典精靈查的字詞",
    "user": {
      "login": "bestian",
      "id": 109048,
      "avatar_url": "https://gravatar.com/avatar/1ea4fcb48144a97a1f68af6d8a302c47?d=https%3A%2F%2Fidenticons.github.com%2F1de5d1df48f548f9d227c6743af88c42.png&r=x",
      "gravatar_id": "1ea4fcb48144a97a1f68af6d8a302c47",
      "url": "https://api.github.com/users/bestian",
      "html_url": "https://github.com/bestian",
      "followers_url": "https://api.github.com/users/bestian/followers",
      "following_url": "https://api.github.com/users/bestian/following{/other_user}",
      "gists_url": "https://api.github.com/users/bestian/gists{/gist_id}",
      "starred_url": "https://api.github.com/users/bestian/starred{/owner}{/repo}",
      "subscriptions_url": "https://api.github.com/users/bestian/subscriptions",
      "organizations_url": "https://api.github.com/users/bestian/orgs",
      "repos_url": "https://api.github.com/users/bestian/repos",
      "events_url": "https://api.github.com/users/bestian/events{/privacy}",
      "received_events_url": "https://api.github.com/users/bestian/received_events",
      "type": "User",
      "site_admin": false
    },
    "labels": [

    ],
    "state": "open",
    "assignee": null,
    "milestone": null,
    "comments": 0,
    "created_at": "2013-08-17T10:18:27Z",
    "updated_at": "2013-08-17T10:18:27Z",
    "closed_at": null,
    "body": "除了成語\r\n或許可以加一個選項\r\n選成語\r\n或選公民知識\r\n\r\n如\r\n[\r\n\"自由\",\r\n\"權利\",\r\n\"權力\",\r\n\"民主\",\r\n\"人權\",\r\n\"社會\",\r\n\"福利\",\r\n\"救濟\",\r\n\"法律\",\r\n\"憲法\",\r\n\"民法\",\r\n\"行政法\"]\r\n\r\n等等，存在另一個檔案中(我找不到如何呼叫出新的內容檔，所以寫在issue這邊~)"
  },
  {
    "url": "https://api.github.com/repos/g0v/g0village-8bit/issues/14",
    "labels_url": "https://api.github.com/repos/g0v/g0village-8bit/issues/14/labels{/name}",
    "comments_url": "https://api.github.com/repos/g0v/g0village-8bit/issues/14/comments",
    "events_url": "https://api.github.com/repos/g0v/g0village-8bit/issues/14/events",
    "html_url": "https://github.com/g0v/g0village-8bit/issues/14",
    "id": 18040560,
    "number": 14,
    "title": "打贏村長後，圖層前後關係錯置",
    "user": {
      "login": "kong0107",
      "id": 4002443,
      "avatar_url": "https://gravatar.com/avatar/9a5ccdc3575869af9da0cec6d4a73c6b?d=https%3A%2F%2Fidenticons.github.com%2Fbd4ee2de2abd72a6215f1d9bcc0fd72a.png&r=x",
      "gravatar_id": "9a5ccdc3575869af9da0cec6d4a73c6b",
      "url": "https://api.github.com/users/kong0107",
      "html_url": "https://github.com/kong0107",
      "followers_url": "https://api.github.com/users/kong0107/followers",
      "following_url": "https://api.github.com/users/kong0107/following{/other_user}",
      "gists_url": "https://api.github.com/users/kong0107/gists{/gist_id}",
      "starred_url": "https://api.github.com/users/kong0107/starred{/owner}{/repo}",
      "subscriptions_url": "https://api.github.com/users/kong0107/subscriptions",
      "organizations_url": "https://api.github.com/users/kong0107/orgs",
      "repos_url": "https://api.github.com/users/kong0107/repos",
      "events_url": "https://api.github.com/users/kong0107/events{/privacy}",
      "received_events_url": "https://api.github.com/users/kong0107/received_events",
      "type": "User",
      "site_admin": false
    },
    "labels": [
      {
        "url": "https://api.github.com/repos/g0v/g0village-8bit/labels/bug",
        "name": "bug",
        "color": "fc2929"
      }
    ],
    "state": "open",
    "assignee": null,
    "milestone": null,
    "comments": 1,
    "created_at": "2013-08-14T08:31:09Z",
    "updated_at": "2013-08-14T20:48:37Z",
    "closed_at": null,
    "body": "![2013-08-14 16 20 38](https://f.cloud.github.com/assets/4002443/960556/e572d100-04ba-11e3-901d-ac0042ffdefd.png)\r\n\r\n環境：\r\n* Google Chrome 23\r\n* Fedora 16\r\n\r\n其他操作紀錄：\r\n* 使用id: kong0107\r\n* 村長說「那沒什麼好說的!戰鬥吧!」後、正式進入戰鬥前，我按了多次空白鍵，疑似在進入戰鬥前又觸發了一次對話。\r\n    * 但再次以相同方式測試（即戰鬥前再次觸發對話），打輸時卻不會有相同結果。\r\n* 打贏的那次是召喚到 c9s\r\n* 打贏的前一次是召喚到 clkao "
  },
  {
    "url": "https://api.github.com/repos/g0v/g0village-8bit/issues/10",
    "labels_url": "https://api.github.com/repos/g0v/g0village-8bit/issues/10/labels{/name}",
    "comments_url": "https://api.github.com/repos/g0v/g0village-8bit/issues/10/comments",
    "events_url": "https://api.github.com/repos/g0v/g0village-8bit/issues/10/events",
    "html_url": "https://github.com/g0v/g0village-8bit/issues/10",
    "id": 17913778,
    "number": 10,
    "title": "平板電腦使用問題",
    "user": {
      "login": "pofeng",
      "id": 43583,
      "avatar_url": "https://gravatar.com/avatar/bfe976def4974c92d5fecc0177efbee2?d=https%3A%2F%2Fidenticons.github.com%2F5d430acb74ac2a69483d1df68b5e6c88.png&r=x",
      "gravatar_id": "bfe976def4974c92d5fecc0177efbee2",
      "url": "https://api.github.com/users/pofeng",
      "html_url": "https://github.com/pofeng",
      "followers_url": "https://api.github.com/users/pofeng/followers",
      "following_url": "https://api.github.com/users/pofeng/following{/other_user}",
      "gists_url": "https://api.github.com/users/pofeng/gists{/gist_id}",
      "starred_url": "https://api.github.com/users/pofeng/starred{/owner}{/repo}",
      "subscriptions_url": "https://api.github.com/users/pofeng/subscriptions",
      "organizations_url": "https://api.github.com/users/pofeng/orgs",
      "repos_url": "https://api.github.com/users/pofeng/repos",
      "events_url": "https://api.github.com/users/pofeng/events{/privacy}",
      "received_events_url": "https://api.github.com/users/pofeng/received_events",
      "type": "User",
      "site_admin": false
    },
    "labels": [

    ],
    "state": "open",
    "assignee": null,
    "milestone": null,
    "comments": 1,
    "created_at": "2013-08-11T15:34:23Z",
    "updated_at": "2013-08-11T16:00:33Z",
    "closed_at": null,
    "body": "( via Ada Hsu ) 平板電腦上不知要如何按 ENTER "
  },
  {
    "url": "https://api.github.com/repos/g0v/g0village-8bit/issues/5",
    "labels_url": "https://api.github.com/repos/g0v/g0village-8bit/issues/5/labels{/name}",
    "comments_url": "https://api.github.com/repos/g0v/g0village-8bit/issues/5/comments",
    "events_url": "https://api.github.com/repos/g0v/g0village-8bit/issues/5/events",
    "html_url": "https://github.com/g0v/g0village-8bit/issues/5",
    "id": 17895083,
    "number": 5,
    "title": "增加黑客松任務 , debuff 高村長",
    "user": {
      "login": "hychen",
      "id": 38706,
      "avatar_url": "https://gravatar.com/avatar/1ee211172ad7e550d0f83987c842dbe0?d=https%3A%2F%2Fidenticons.github.com%2Ffde68dedaec43289f5f7d9c8fa7ff53d.png&r=x",
      "gravatar_id": "1ee211172ad7e550d0f83987c842dbe0",
      "url": "https://api.github.com/users/hychen",
      "html_url": "https://github.com/hychen",
      "followers_url": "https://api.github.com/users/hychen/followers",
      "following_url": "https://api.github.com/users/hychen/following{/other_user}",
      "gists_url": "https://api.github.com/users/hychen/gists{/gist_id}",
      "starred_url": "https://api.github.com/users/hychen/starred{/owner}{/repo}",
      "subscriptions_url": "https://api.github.com/users/hychen/subscriptions",
      "organizations_url": "https://api.github.com/users/hychen/orgs",
      "repos_url": "https://api.github.com/users/hychen/repos",
      "events_url": "https://api.github.com/users/hychen/events{/privacy}",
      "received_events_url": "https://api.github.com/users/hychen/received_events",
      "type": "User",
      "site_admin": false
    },
    "labels": [
      {
        "url": "https://api.github.com/repos/g0v/g0village-8bit/labels/enhancement",
        "name": "enhancement",
        "color": "84b6eb"
      }
    ],
    "state": "open",
    "assignee": null,
    "milestone": null,
    "comments": 0,
    "created_at": "2013-08-10T06:23:03Z",
    "updated_at": "2013-08-10T06:25:37Z",
    "closed_at": null,
    "body": "為了讓勇者比較好打倒高村長, 以及鼓勵commit, 所以黑客松高村長HP會下降.\r\n.\r\n只要任一g0v專案有 1 commit時, 高村長 HP - 1., 當黑客松結束時, 村長HP不再受這debuff影響.\r\n\r\n公式: 高村長總HP = 原始HP - 當日 commit 數"
  }
]